http_bruteforce/__init__.py
http_bruteforce/http_bruteforce.py
http_bruteforce-1.0.dist-info/METADATA
http_bruteforce-1.0.dist-info/WHEEL
http_bruteforce-1.0.dist-info/entry_points.txt
http_bruteforce-1.0.dist-info/top_level.txt
http_bruteforce-1.0.dist-info/RECORD
