Metadata-Version: 2.1
Name: http-bruteforce
Version: 1.0
Requires-Dist: requests
Requires-Dist: argparse
Requires-Dist: termcolor
